bytelogger/__init__.py
bytelogger/better_logger.py
bytelogger/get_logs.py
bytelogger-2.1.3.dist-info/licenses/LICENSE
bytelogger-2.1.3.dist-info/METADATA
bytelogger-2.1.3.dist-info/WHEEL
bytelogger-2.1.3.dist-info/top_level.txt
bytelogger-2.1.3.dist-info/RECORD
