Metadata-Version: 2.4
Name: bytelogger
Version: 2.1.3
Summary: bytelogger: Is a simple tool for logging and debuging your code. You can easyly turn debug_mode and log mode on or off.
Home-page: https://github.com/n0byte/bytelogger
Author: n0byte
Classifier: Programming Language :: Python :: 3
Classifier: License :: OSI Approved :: MIT License
Classifier: Operating System :: OS Independent
Requires-Python: >=3.6
License-File: LICENSE
Dynamic: author
Dynamic: classifier
Dynamic: description
Dynamic: description-content-type
Dynamic: home-page
Dynamic: license-file
Dynamic: requires-python
Dynamic: summary
